nxgdb/__init__.py
nxgdb/circbuf.py
nxgdb/debug.py
nxgdb/diagnose.py
nxgdb/dmesg.py
nxgdb/fs.py
nxgdb/gcore.py
nxgdb/lists.py
nxgdb/macros.py
nxgdb/memcheck.py
nxgdb/memdump.py
nxgdb/memleak.py
nxgdb/mm.py
nxgdb/net.py
nxgdb/prefix.py
nxgdb/profile.py
nxgdb/rpmsg.py
nxgdb/stack.py
nxgdb/thread.py
nxgdb/uorb.py
nxgdb/utils.py
nxgdb/wdog.py
nxgdb/wqueue.py
nxgdb/protocols/circbuf.py
nxgdb/protocols/fs.py
nxgdb/protocols/mm.py
nxgdb/protocols/thread.py
nxgdb/protocols/uorb.py
nxgdb/protocols/value.py
nxgdb/protocols/wdog.py
nxgdb/protocols/wqueue.py
nxgdb-0.0.1.2.dist-info/METADATA
nxgdb-0.0.1.2.dist-info/WHEEL
nxgdb-0.0.1.2.dist-info/top_level.txt
nxgdb-0.0.1.2.dist-info/RECORD
